{
  "categoryName": "Interests",
  "categories": [
    {
      "categoryID": "294",
      "parentID": "304",
      "subjectID": "7",
      "categoryName": "Flying",
      "categoryDescription": "I'm in the CAP and I want to fly when I'm older.",
      "videosCount": "101",
      "forumCategoryID": "163"
    },
    {
      "categoryID": "285",
      "parentID": "304",
      "subjectID": "7",
      "categoryName": "Cars",
      "categoryDescription": "I am interested in fast and cool looking cars.",
      "videosCount": "38",
      "forumCategoryID": "163"
    },
    {
      "categoryID": "337",
      "parentID": "304",
      "subjectID": "7",
      "categoryName": "Lacrosse",
      "categoryDescription": "I play for Olympus.",
      "videosCount": "5",
      "forumCategoryID": "163"
    },
    {
      "categoryID": "301",
      "parentID": "304",
      "subjectID": "7",
      "categoryName": "Music",
      "categoryDescription": "I like lots of music and I want to make my own.",
      "videosCount": "43",
      "forumCategoryID": "163"
    },
    {
      "categoryID": "297",
      "parentID": "304",
      "subjectID": "7",
      "categoryName": "Video Games",
      "categoryDescription": "I play lots of video games with friends.",
      "videosCount": "70",
      "forumCategoryID": "163"
    }
  ]
}